orcid2vivo.py
orcid2vivo_loader.py
orcid2vivo_service.py
orcid2vivo-0.10.0.data/scripts/orcid2vivo.py
orcid2vivo-0.10.0.data/scripts/orcid2vivo_loader.py
orcid2vivo-0.10.0.data/scripts/orcid2vivo_service.py
orcid2vivo-0.10.0.dist-info/DESCRIPTION.rst
orcid2vivo-0.10.0.dist-info/METADATA
orcid2vivo-0.10.0.dist-info/RECORD
orcid2vivo-0.10.0.dist-info/WHEEL
orcid2vivo-0.10.0.dist-info/metadata.json
orcid2vivo-0.10.0.dist-info/pbr.json
orcid2vivo-0.10.0.dist-info/top_level.txt
orcid2vivo_app/__init__.py
orcid2vivo_app/affiliations.py
orcid2vivo_app/bio.py
orcid2vivo_app/fundings.py
orcid2vivo_app/utility.py
orcid2vivo_app/vivo_namespace.py
orcid2vivo_app/vivo_uri.py
orcid2vivo_app/works.py
